{
  "$schema": "https://schemas.r3e.network/miniapp-manifest/v1.json",
  "id": "miniapp-event-ticket-pass",
  "name": "Event Ticket",
  "name_zh": "活动门票",
  "version": "1.0.0",
  "description": "Issue NEP-11 event tickets with QR check-in.",
  "description_zh": "活动门票 - Neo N3 去中心化应用",
  "category": "social",
  "category_name": "Social",
  "category_name_zh": "社交",
  "tags": [
    "tickets",
    "events",
    "qr"
  ],
  "developer": {
    "name": "R3E Network",
    "email": "dev@r3e.network",
    "website": "https://r3e.network"
  },
  "contracts": {
    "neo-n3-mainnet": "0x8c65b320d7b7ba8806dac3e12f7e62b33474c74e",
    "neo-n3-testnet": ""
  },
  "supported_networks": [
    "neo-n3-mainnet"
  ],
  "default_network": "neo-n3-mainnet",
  "urls": {
    "entry": "/miniapps/event-ticket-pass/index.html",
    "icon": "/miniapps/event-ticket-pass/logo.jpg",
    "banner": "/miniapps/event-ticket-pass/banner.jpg"
  },
  "permissions": [
    "invoke:primary",
    "read:blockchain"
  ],
  "features": {
    "stateless": true,
    "offlineSupport": false,
    "deeplink": "neomainapp://event-ticket-pass"
  },
  "stateSource": {
    "type": "smart-contract",
    "chain": "neo-n3-mainnet",
    "endpoints": [
      "https://neo.coz.io/mainnet"
    ]
  },
  "platform": {
    "analytics": true,
    "comments": true,
    "ratings": true,
    "transactions": true
  },
  "createdAt": "2026-01-01T00:00:00Z",
  "updatedAt": "2026-01-26T12:00:00Z"
}